cryptonets_python_sdk/__init__.py
cryptonets_python_sdk/api_h.h
cryptonets_python_sdk/flags.py
cryptonets_python_sdk/img_utils.py
cryptonets_python_sdk/library.py
cryptonets_python_sdk/library_loader.py
cryptonets_python_sdk/session.py
cryptonets_python_sdk/idl/__init__.py
cryptonets_python_sdk/idl/gen/__init__.py
cryptonets_python_sdk/idl/gen/privateid_types.py
cryptonets_python_sdk-2.0.2.dist-info/licenses/LICENSE
cryptonets_python_sdk-2.0.2.dist-info/METADATA
cryptonets_python_sdk-2.0.2.dist-info/WHEEL
cryptonets_python_sdk-2.0.2.dist-info/top_level.txt
cryptonets_python_sdk-2.0.2.dist-info/RECORD
