Metadata-Version: 2.4
Name: cryptonets_python_sdk
Version: 2.0.2
Summary: Cryptonets SDK Library for Python
Home-page: https://private.id/
Author: Private Identity
Author-email: support@private.id
License: Proprietary
Project-URL: Bug Reports, https://github.com/prividentity/cryptonets-python-sdk/issues
Project-URL: Source, https://github.com/prividentity/cryptonets-python-sdk
Project-URL: Documentation, https://github.com/prividentity/cryptonets-python-sdk/tree/2.0.2/README.md
Project-URL: Release Notes, https://github.com/prividentity/cryptonets-python-sdk/blob/2.0.2/CHANGELOG.md
Keywords: privateid,cryptonets,face identification,biometrics,privacy
Platform: any
Classifier: Development Status :: 5 - Production/Stable
Classifier: Intended Audience :: Developers
Classifier: License :: Other/Proprietary License
Classifier: Programming Language :: Python
Classifier: Operating System :: OS Independent
Classifier: Topic :: Software Development
Classifier: Topic :: Scientific/Engineering :: Artificial Intelligence
Classifier: Topic :: Security :: Cryptography
Requires-Python: >=3.10
License-File: LICENSE
Requires-Dist: numpy>=1.21.0
Requires-Dist: pillow>=9.1.0
Requires-Dist: boto3>=1.24.0
Requires-Dist: tqdm>=4.64.0
Requires-Dist: exifread>=3.0.0
Requires-Dist: cffi>=1.15.0
Requires-Dist: msgspec>=0.20.0
Requires-Dist: pyyaml>=6.0.2
Provides-Extra: dev
Requires-Dist: pytest>=6.2.0; extra == "dev"
Requires-Dist: matplotlib>=3.5.0; extra == "dev"
Requires-Dist: datamodel-code-generator>=0.52.0; extra == "dev"
Dynamic: author
Dynamic: author-email
Dynamic: classifier
Dynamic: description
Dynamic: description-content-type
Dynamic: home-page
Dynamic: keywords
Dynamic: license
Dynamic: license-file
Dynamic: platform
Dynamic: project-url
Dynamic: provides-extra
Dynamic: requires-dist
Dynamic: requires-python
Dynamic: summary
